pytorch_spear-0.1.0.dist-info/DESCRIPTION.rst
pytorch_spear-0.1.0.dist-info/METADATA
pytorch_spear-0.1.0.dist-info/RECORD
pytorch_spear-0.1.0.dist-info/WHEEL
pytorch_spear-0.1.0.dist-info/metadata.json
pytorch_spear-0.1.0.dist-info/top_level.txt
spear/__init__.py
spear/__init__.pyc
spear/attacks/BasicIterativeMethod.py
spear/attacks/BasicIterativeMethod.pyc
spear/attacks/CarliniWagner.py
spear/attacks/DeepFool.py
spear/attacks/DeepFool.pyc
spear/attacks/FGSM.py
spear/attacks/FGSM.pyc
spear/attacks/__init__.py
spear/attacks/__init__.pyc
