Metadata-Version: 2.0
Name: pytorch-spear
Version: 0.1.0
Summary: Library for benchmarking adversarial defence methods
Home-page: http://github.com/tejus-gupta/spear
Author: Tejus Gupta
Author-email: UNKNOWN
License: MIT
Platform: UNKNOWN
Requires-Dist: torchvision
